CHANGELOG.txt
LICENSE.TXT
MANIFEST.in
README.txt
cal_lib.py
setup.py
ebrahimcla.egg-info/PKG-INFO
ebrahimcla.egg-info/SOURCES.txt
ebrahimcla.egg-info/dependency_links.txt
ebrahimcla.egg-info/top_level.txt